proxytools/__init__.py
proxytools/cli.py
proxytools/exceptions.py
proxytools/models.py
proxytools/proxychecker.py
proxytools/proxyfetcher.py
proxytools/proxylist.py
proxytools/requests.py
proxytools/superproxy.py
proxytools/utils.py
proxytools/fetchers/__init__.py
proxytools/fetchers/freeproxylistnet.py
proxytools/fetchers/gatherproxy.py
proxytools/fetchers/hidemyname.py
proxytools/fetchers/hidester.py
proxytools/fetchers/spysone.py
proxytools/fetchers/torvpn.py
proxytools-0.0.3.dist-info/METADATA
proxytools-0.0.3.dist-info/RECORD
proxytools-0.0.3.dist-info/WHEEL
proxytools-0.0.3.dist-info/entry_points.txt
proxytools-0.0.3.dist-info/top_level.txt
