Metadata-Version: 2.1
Name: proxytools
Version: 0.0.3
Summary: http://github.com/vgavro/proxytools
Home-page: http://github.com/vgavro/proxytools
Author: Victor Gavro
Author-email: vgavro@gmail.com
License: BSD
Platform: UNKNOWN
Classifier: Environment :: Web Environment
Classifier: Intended Audience :: Developers
Classifier: License :: OSI Approved :: BSD License
Classifier: Programming Language :: Python
Classifier: Topic :: Internet :: WWW/HTTP :: Dynamic Content
Classifier: Topic :: Software Development :: Libraries :: Python Modules
Requires-Dist: requests[socks] (>=2.18.4)
Requires-Dist: pysocks (>=1.6.8)
Requires-Dist: gevent
Requires-Dist: netaddr
Requires-Dist: pycountry
Requires-Dist: pycountry-convert (>=0.6)
Requires-Dist: pytimeparse
Requires-Dist: lxml (>=3.7.3)
Requires-Dist: js2py
Requires-Dist: cssselect (>=1.0.1)
Requires-Dist: click
Requires-Dist: pyyaml
Requires-Dist: ipython
Requires-Dist: pdbpp
Requires-Dist: coloredlogs
Requires-Dist: requests-mock
Requires-Dist: pytest (>=1.3)
Requires-Dist: pytest-cov
Requires-Dist: pytest-flake8
